{
  "title": "前車煞不住倒退嚕　5秒和死神擦身過",
  "id": "20150829/680647",
  "link": "http://www.appledaily.com.tw/realtimenews/article/new/20150829/680647/",
  "comments": [
    {
      "created_time": "2015-08-29T14:57:59+0000",
      "from": {
        "name": "銀行車貸_陳小姐",
        "category": "Community",
        "id": "1114539648559967"
      },
      "message": "開車真的要專心注意加小心",
      "can_remove": false,
      "like_count": 1,
      "user_likes": false,
      "id": "998347760186813_998387520182837"
    },
    {
      "created_time": "2015-08-29T14:50:58+0000",
      "from": {
        "name": "銀行汽車貸款_林先生",
        "category": "Fictional Character",
        "id": "430793447090788"
      },
      "message": "再度證明女生出車禍一直叫",
      "can_remove": false,
      "like_count": 1,
      "user_likes": false,
      "id": "998347760186813_998385233516399"
    },
    {
      "created_time": "2015-08-29T14:42:53+0000",
      "from": {
        "name": "賴世和",
        "id": "100008849221578"
      },
      "message": "那位女騎士是不要命膩",
      "can_remove": false,
      "like_count": 1,
      "user_likes": false,
      "id": "998347760186813_998382580183331"
    },
    {
      "created_time": "2015-08-29T14:18:26+0000",
      "from": {
        "name": "Sean Liao",
        "id": "1241148970"
      },
      "message": "嗯⋯QRV的引擎在冒煙，掛了吧！那段坡度很大，所以倒退嚕⋯傳說中的天府路",
      "can_remove": false,
      "like_count": 0,
      "user_likes": false,
      "id": "998347760186813_998374506850805"
    },
    {
      "created_time": "2015-08-29T13:56:47+0000",
      "from": {
        "name": "陳力",
        "id": "100009208194435"
      },
      "message": "死白痴！！！",
      "can_remove": false,
      "like_count": 0,
      "user_likes": false,
      "id": "998347760186813_998369060184683"
    },
    {
      "created_time": "2015-08-29T13:47:07+0000",
      "from": {
        "name": "李邁詔",
        "id": "100006822818782"
      },
      "message": "這種情況我遇過一次，對方撞車後暈倒在車上，道路又是有點下坡，才往後滑，我發現不對勁立刻刹車打倒檔，還好後面沒車，加上沒多久就到平路了，才沒發生意外",
      "can_remove": false,
      "like_count": 0,
      "user_likes": false,
      "id": "998347760186813_998366810184908"
    },
    {
      "created_time": "2015-08-29T13:37:21+0000",
      "from": {
        "name": "蔡秉憲",
        "id": "1792332777"
      },
      "message": "這路段常出事",
      "can_remove": false,
      "like_count": 1,
      "user_likes": false,
      "id": "998347760186813_998363013518621"
    },
    {
      "created_time": "2015-08-29T13:32:50+0000",
      "from": {
        "name": "梁嘉逸",
        "id": "100000288643247"
      },
      "message": "青山路 新莊往龜山。",
      "can_remove": false,
      "like_count": 0,
      "user_likes": false,
      "id": "998347760186813_998361903518732"
    },
    {
      "created_time": "2015-08-29T13:32:06+0000",
      "from": {
        "name": "戴久芫",
        "id": "1012956951"
      },
      "message": "箱型車的引擎掛了在冒煙",
      "can_remove": false,
      "like_count": 0,
      "user_likes": false,
      "id": "998347760186813_998361766852079"
    },
    {
      "created_time": "2015-08-29T13:30:45+0000",
      "from": {
        "name": "陳德",
        "id": "100005633596107"
      },
      "message": "開車最怕這種，七月半鴉，不知死活，真的馬路如虎口",
      "can_remove": false,
      "like_count": 2,
      "user_likes": false,
      "id": "998347760186813_998361546852101"
    }
  ]
}