{
  "title": "【更新】若發行波多野卡　議員：杯葛悠卡公司公股預算",
  "id": "20150830/680823",
  "link": "http://www.appledaily.com.tw/realtimenews/article/new/20150830/680823/",
  "comments": [
    {
      "created_time": "2015-08-30T03:58:58+0000",
      "from": {
        "name": "Ulysses Hung",
        "id": "100000174086607"
      },
      "message": "吃飽太閒哦，能不能去關心一下油、電是不是太貴，不是該盯緊政府股市怎麼救，想想怎麼拜托當老闆的給員工加薪，喵的勒~人民都已經過的很痛苦了，看看你們現在還在幹嘛?",
      "can_remove": false,
      "like_count": 0,
      "user_likes": false,
      "id": "927901720634743_927924123965836"
    },
    {
      "created_time": "2015-08-30T03:58:28+0000",
      "from": {
        "name": "Yi-ling Chang",
        "id": "1851368508"
      },
      "message": "這算公然威脅吧！議員是黑道嗎？",
      "can_remove": false,
      "like_count": 0,
      "user_likes": false,
      "id": "927901720634743_927924063965842"
    },
    {
      "created_time": "2015-08-30T03:57:12+0000",
      "from": {
        "name": "黃裕偉",
        "id": "100000328423200"
      },
      "message": "怎麼不見查國防部 阿帕契 鼎新 014\n就只能容忍KMT安全下莊\n說好的完全執政 完全負責也是口號而已",
      "can_remove": false,
      "like_count": 0,
      "user_likes": false,
      "id": "927901720634743_927923730632542"
    },
    {
      "created_time": "2015-08-30T03:57:08+0000",
      "from": {
        "name": "王元萬",
        "id": "100006112638576"
      },
      "message": "媽的真的那顆腦真的只值一塊錢",
      "can_remove": false,
      "like_count": 0,
      "user_likes": false,
      "id": "927901720634743_927923713965877"
    },
    {
      "created_time": "2015-08-30T03:55:52+0000",
      "from": {
        "name": "熊維尼",
        "id": "100007223539178"
      },
      "message": "笑話\n人家悠遊卡都印好了 你說不賣就不賣?\n當初教育部長說課本都印好了 新書得用 課綱怎能不實施時\n怎麼不見你們這群出來吭個聲?",
      "can_remove": false,
      "like_count": 1,
      "user_likes": false,
      "id": "927901720634743_927923513965897"
    },
    {
      "created_time": "2015-08-30T03:54:14+0000",
      "from": {
        "name": "郭榮彬",
        "id": "100000432818240"
      },
      "message": "議員們自己中計了都不知道，還杯葛勒，到時市政府會直接把悠遊卡價值炒高，名正言順出脫官股，一樣能解套，且為市政府帶來更多資金。",
      "can_remove": false,
      "like_count": 0,
      "user_likes": false,
      "id": "927901720634743_927923197299262"
    },
    {
      "created_time": "2015-08-30T03:52:18+0000",
      "from": {
        "name": "Jiazhe Li",
        "id": "100000077863769"
      },
      "message": "你們這些白癡議員，要來惡搞悠遊卡，你們他媽的可不可以先開個酒駕、貪污這些議題先開始？幹嗎？要選舉在騙選票是不是？作秀！",
      "can_remove": false,
      "like_count": 0,
      "user_likes": false,
      "id": "927901720634743_927922483966000"
    },
    {
      "created_time": "2015-08-30T03:47:57+0000",
      "from": {
        "name": "Arnold Liu",
        "id": "100000306049353"
      },
      "message": "“垃圾議員”",
      "can_remove": false,
      "like_count": 1,
      "user_likes": false,
      "id": "927901720634743_927921737299408"
    },
    {
      "created_time": "2015-08-30T03:44:02+0000",
      "from": {
        "name": "Chun Hui Weng",
        "id": "100004129360513"
      },
      "message": "如果柯P同意台北市設立性專區，那我覺得這團隊言行一致，沒什麼好批評，否則市府團隊就是瞧不起這職業，AV女優跟性工作者不都一樣靠女性本能賺錢為什麽有差別待遇。\n再說如果成立性專區有一個很紅的性工作者像太陽花女王，半官方的悠遊卡公司會以她當封面嗎？",
      "can_remove": false,
      "like_count": 0,
      "user_likes": false,
      "id": "927901720634743_927920857299496"
    },
    {
      "created_time": "2015-08-30T03:43:14+0000",
      "from": {
        "name": "Cynthia Weng",
        "id": "100006882186732"
      },
      "message": "Jun 17, 2014 - 名嘴陳東豪爆台北市議員參選人徐弘庭曾在皮夾中掏出保險套。 ... 市議員參選人徐弘庭多年前曾在一場記者會上，掏皮夾時不小心把保險套掉出來。\n哈哈哈!",
      "can_remove": false,
      "like_count": 1,
      "user_likes": false,
      "id": "927901720634743_927920720632843"
    },
    {
      "created_time": "2015-08-30T03:39:20+0000",
      "from": {
        "name": "陳建名",
        "id": "100009413181683"
      },
      "message": "為何要用日本明星，臺灣是沒人可用嗎？",
      "can_remove": false,
      "like_count": 0,
      "user_likes": false,
      "id": "927901720634743_927919947299587"
    },
    {
      "created_time": "2015-08-30T03:36:41+0000",
      "from": {
        "name": "莊慶輝",
        "id": "1796128297"
      },
      "message": "一個標準才可以，犯錯就批，管牠是藍是綠！臺灣共合國要有是非，否則冒著戰爭危險搞臺獨是為什麼呢！",
      "can_remove": false,
      "like_count": 0,
      "user_likes": false,
      "id": "927901720634743_927919263966322"
    },
    {
      "created_time": "2015-08-30T03:35:23+0000",
      "from": {
        "name": "Si Wei",
        "id": "100001582086523"
      },
      "message": "看了這些人的意見後......開賣後我也要加入搶購的行列！",
      "can_remove": false,
      "like_count": 2,
      "user_likes": false,
      "id": "927901720634743_927918503966398"
    },
    {
      "created_time": "2015-08-30T03:34:27+0000",
      "from": {
        "name": "阮耀田",
        "id": "100000573734295"
      },
      "message": "真正有本事是說服民眾不買來強化你們反對的正當性而非恐嚇不給預算\n因為這方式是民意代表最廉價也最下下等的作為不是嗎?",
      "can_remove": false,
      "like_count": 2,
      "user_likes": false,
      "id": "927901720634743_927918240633091"
    },
    {
      "created_time": "2015-08-30T03:34:06+0000",
      "from": {
        "name": "Si Wei",
        "id": "100001582086523"
      },
      "message": "越看越火.....這些人對其他社會議題不聞不問....對一張卡一直吵新聞.....",
      "can_remove": false,
      "like_count": 3,
      "user_likes": false,
      "id": "927901720634743_927918187299763"
    },
    {
      "created_time": "2015-08-30T03:33:59+0000",
      "from": {
        "name": "莫凱鈞",
        "id": "100000571422263"
      },
      "message": "道德勸說不行 只好對決 我支持",
      "can_remove": false,
      "like_count": 0,
      "user_likes": false,
      "id": "927901720634743_927918157299766"
    },
    {
      "created_time": "2015-08-30T03:30:32+0000",
      "from": {
        "name": "郭增壽",
        "id": "100009371676503"
      },
      "message": "好吧！女星只要以前露點拍過照的現在穿回衣服的全面下架好了！",
      "can_remove": false,
      "like_count": 2,
      "user_likes": false,
      "id": "927901720634743_927917287299853"
    },
    {
      "created_time": "2015-08-30T03:30:29+0000",
      "from": {
        "name": "Tzuyi Yang",
        "id": "100001093854373"
      },
      "message": "這些官員長官們都睡了波奶多吧~",
      "can_remove": false,
      "like_count": 0,
      "user_likes": false,
      "id": "927901720634743_927917277299854"
    },
    {
      "created_time": "2015-08-30T03:27:47+0000",
      "from": {
        "name": "黃漢賢",
        "id": "100000277403881"
      },
      "message": "不想看不要買就好台灣一堆噁心的人,一方面上網搜尋免費A片,一方面大力撻伐此事情,請問一下全台灣幾百萬台灣男性甚麼時候用合法手段看到日本A片了?大家幾乎都是用少數的金錢或是免費的手段看到的從早期電腦尚未普及的階段,就可以訂購一片40.50的A片只要勾一勾訂購單馬上送府,現在更方便了上網就找的到,講難聽一點全部違法,噁心的台灣人一會看片一會痛罵,高舉道德大旗卻不知自己違反道德的一面,合法拍片的AV女優代言你們就痛罵我真想請問這些委員你們是去買一片幾千日圓的合法A片還是訂購1片50元的非法A片甚至免費的呢?你們到底道德高尚到哪去啊",
      "can_remove": false,
      "like_count": 3,
      "user_likes": false,
      "id": "927901720634743_927916773966571"
    },
    {
      "created_time": "2015-08-30T03:23:01+0000",
      "from": {
        "name": "李昭富",
        "id": "100006617265959"
      },
      "message": "去禁一下手遊廣告上的性暗示吧\n有這能奈嗎\n這些議員真的是在做事嗎",
      "can_remove": false,
      "like_count": 2,
      "user_likes": false,
      "id": "927901720634743_927914883966760"
    },
    {
      "created_time": "2015-08-30T03:21:45+0000",
      "from": {
        "name": "楊富強",
        "id": "1087746320"
      },
      "message": "住台北的，選舉的時候你們自己處理一下",
      "can_remove": false,
      "like_count": 1,
      "user_likes": false,
      "id": "927901720634743_927914267300155"
    },
    {
      "created_time": "2015-08-30T03:21:42+0000",
      "from": {
        "name": "張簡德宗",
        "id": "100000361612397"
      },
      "message": "三個人看起來心術不正的感覺，一個幽靈公車，一個也是神d前悠遊卡特助",
      "can_remove": false,
      "like_count": 2,
      "user_likes": false,
      "id": "927901720634743_927914233966825"
    },
    {
      "created_time": "2015-08-30T03:20:24+0000",
      "from": {
        "name": "謝清旭",
        "id": "100003072936661"
      },
      "message": "要去哪買？",
      "can_remove": false,
      "like_count": 1,
      "user_likes": false,
      "id": "927901720634743_927913507300231"
    },
    {
      "created_time": "2015-08-30T03:18:40+0000",
      "from": {
        "name": "Nini Chang",
        "id": "100000496644977"
      },
      "message": "戴季全真是神經病，吃大便的變態",
      "can_remove": false,
      "like_count": 0,
      "user_likes": false,
      "id": "927901720634743_927913070633608"
    },
    {
      "created_time": "2015-08-30T03:15:20+0000",
      "from": {
        "name": "Nic Li",
        "id": "100005391194870"
      },
      "message": "真是很閒是吧\n可以多做點有意義的事嗎?",
      "can_remove": false,
      "like_count": 2,
      "user_likes": false,
      "id": "927901720634743_927912300633685"
    },
    {
      "created_time": "2015-08-30T03:12:32+0000",
      "from": {
        "name": "李漢宗",
        "id": "1535577378"
      },
      "message": "國民黨這些議員超骯髒 我要買波多卡",
      "can_remove": false,
      "like_count": 3,
      "user_likes": false,
      "id": "927901720634743_927911440633771"
    },
    {
      "created_time": "2015-08-30T03:10:13+0000",
      "from": {
        "name": "馮仁傑",
        "id": "100000260264637"
      },
      "message": "K黨立委議員真的很忙碌，每天都在開記者會，不是罵柯P就是罵賴清德。罵柯P來掩護朱立倫，罵賴清德來掩護李全教。都執政幾年了，拿不出政績，只有一個接一個的跳票政策。",
      "can_remove": false,
      "like_count": 19,
      "user_likes": false,
      "id": "927901720634743_927910840633831"
    },
    {
      "created_time": "2015-08-30T03:08:35+0000",
      "from": {
        "name": "Vicki Ma",
        "id": "100005871910241"
      },
      "message": "偽善\n我認為AV女優不妥，但是並非無限上綱。\n尤其恐嚇凍結預算，算不算是恐嚇罪呢?\n你不聽我的，就掐死你???\n人民賦予議員的權利，並不包括任性。",
      "can_remove": false,
      "like_count": 7,
      "user_likes": false,
      "id": "927901720634743_927910490633866"
    },
    {
      "created_time": "2015-08-30T03:08:27+0000",
      "from": {
        "name": "陳家賢",
        "id": "100000759078076"
      },
      "message": "只是唯美照片大驚小怪 反對的人我看都是用有色的眼光去看待 當你們去看藝術時都用藝術眼光來看 AV女優的唯美照片卻是色情眼光看待 差別待遇真大  都什麼世紀了 還在過於保守的觀念 杯葛的議員你(妳)們是羨慕還是忌妒女優美啊？ 去做其他該做的 少在這個事件演戲!!",
      "can_remove": false,
      "like_count": 5,
      "user_likes": false,
      "id": "927901720634743_927910483967200"
    },
    {
      "created_time": "2015-08-30T03:03:55+0000",
      "from": {
        "name": "賴昂享",
        "id": "100000052453362"
      },
      "message": "政治人物慣用手法出現了!只會對預算下手....有沒有想過有些預算是間接關係到民眾?這種作法只會惡化!從來都沒想過如何化解問題....因為看太多!所以我很痛恨所有黨派!再照這種模式玩下去，台灣就真的變鬼島了.....",
      "can_remove": false,
      "like_count": 3,
      "user_likes": false,
      "id": "927901720634743_927909623967286"
    },
    {
      "created_time": "2015-08-30T03:03:19+0000",
      "from": {
        "name": "林永宏",
        "id": "1832920504"
      },
      "message": "好清高呀\n政治人物比，AV女优高尚?\n><",
      "can_remove": false,
      "like_count": 14,
      "user_likes": false,
      "id": "927901720634743_927909543967294"
    },
    {
      "created_time": "2015-08-30T02:59:02+0000",
      "from": {
        "name": "鐘通豪",
        "id": "100000046993690"
      },
      "message": "好大的官威喔～妳好大我好怕～",
      "can_remove": false,
      "like_count": 4,
      "user_likes": false,
      "id": "927901720634743_927902900634625"
    }
  ]
}