{
  "title": "鐵鎚打爆女師頭　狠男判死",
  "id": "20150909/687839",
  "link": "http://www.appledaily.com.tw/realtimenews/article/new/20150909/687839/",
  "comments": [
    {
      "created_time": "2015-09-09T05:53:40+0000",
      "from": {
        "name": "Jason Wen",
        "id": "100005951898599"
      },
      "message": "還拖什麼 趕快執行",
      "can_remove": false,
      "like_count": 0,
      "user_likes": false,
      "id": "859811910782549_859868150776925"
    },
    {
      "created_time": "2015-09-09T05:49:05+0000",
      "from": {
        "name": "林秘滷",
        "id": "100004425844685"
      },
      "message": "既然如此…………就快點執行吧！",
      "can_remove": false,
      "like_count": 0,
      "user_likes": false,
      "id": "859811910782549_859867154110358"
    },
    {
      "created_time": "2015-09-09T04:40:22+0000",
      "from": {
        "name": "閔敏",
        "id": "100007772287226"
      },
      "message": "廢渣不死刑就太沒天理了",
      "can_remove": false,
      "like_count": 0,
      "user_likes": false,
      "id": "859811910782549_859849247445482"
    },
    {
      "created_time": "2015-09-09T04:33:30+0000",
      "from": {
        "name": "薛雋達",
        "id": "100001843958079"
      },
      "message": "人杈團體最喜歡這人渣",
      "can_remove": false,
      "like_count": 0,
      "user_likes": false,
      "id": "859811910782549_859847504112323"
    },
    {
      "created_time": "2015-09-09T03:51:00+0000",
      "from": {
        "name": "周東亮",
        "id": "100006797026831"
      },
      "message": "去死吧！人渣",
      "can_remove": false,
      "like_count": 0,
      "user_likes": false,
      "id": "859811910782549_859835737446833"
    },
    {
      "created_time": "2015-09-09T03:37:41+0000",
      "from": {
        "name": "Chun Lou",
        "id": "100000154371092"
      },
      "message": "死刑真是便宜他了",
      "can_remove": false,
      "like_count": 0,
      "user_likes": false,
      "id": "859811910782549_859832300780510"
    },
    {
      "created_time": "2015-09-09T03:30:29+0000",
      "from": {
        "name": "王義雄",
        "id": "100003938865142"
      },
      "message": "\"表示因酒醉無法控制\"  無法控制，還能走路還能騎車還能拿榔頭殺人，希望真的是判死刑，不要變成有期徒刑而已，如果怕廢死聯盟說話，那就判關到死",
      "can_remove": false,
      "like_count": 0,
      "user_likes": false,
      "id": "859811910782549_859830510780689"
    },
    {
      "created_time": "2015-09-09T03:20:02+0000",
      "from": {
        "name": "柯諭驊",
        "id": "100001856221254"
      },
      "message": "以前有黑道有\n要錢不要命\n要命不要錢\n這種說法\n現在黑道之所以讓看衰小\n因為失去了道\n就變成下三濫\n想想張錫銘雖然是黑道\n但在當地很受民眾尊重\n可以想想這是為什麼?\n多次警察圍捕\n徒勞無功\n都是鄉親們暗中幫忙通風報信",
      "can_remove": false,
      "like_count": 0,
      "user_likes": false,
      "id": "859811910782549_859827584114315"
    },
    {
      "created_time": "2015-09-09T03:12:56+0000",
      "from": {
        "name": "Jacky Chen",
        "id": "100000227734505"
      },
      "message": "能不能把該死的，還在浪費錢吃牢飯的那些判死不槍斃的，這一次全拉去斃了，法務部展現一下決心，做做好事吧！",
      "can_remove": false,
      "like_count": 1,
      "user_likes": false,
      "id": "859811910782549_859824094114664"
    },
    {
      "created_time": "2015-09-09T03:07:57+0000",
      "from": {
        "name": "Colivaro Bruce",
        "id": "100009770564530"
      },
      "message": "廢話少說，早死早超生",
      "can_remove": false,
      "like_count": 1,
      "user_likes": false,
      "id": "859811910782549_859822560781484"
    },
    {
      "created_time": "2015-09-09T03:04:26+0000",
      "from": {
        "name": "Betty Lin",
        "id": "1077315439"
      },
      "message": "殘忍",
      "can_remove": false,
      "like_count": 1,
      "user_likes": false,
      "id": "859811910782549_859820137448393"
    },
    {
      "created_time": "2015-09-09T03:02:55+0000",
      "from": {
        "name": "彭体熊",
        "id": "100000256047434"
      },
      "message": "死好 垃圾",
      "can_remove": false,
      "like_count": 1,
      "user_likes": false,
      "id": "859811910782549_859817874115286"
    },
    {
      "created_time": "2015-09-09T03:01:31+0000",
      "from": {
        "name": "Chen Jerome",
        "id": "100000244634510"
      },
      "message": "祈禱廢死支持者變成被害者家屬",
      "can_remove": false,
      "like_count": 0,
      "user_likes": false,
      "id": "859811910782549_859816354115438"
    },
    {
      "created_time": "2015-09-09T03:00:51+0000",
      "from": {
        "name": "宋亦岡",
        "id": "100002383297045"
      },
      "message": "別指望太高，這只是地院審理，到了高等及最高法院時還不一定會斃了這畜牲。",
      "can_remove": false,
      "like_count": 5,
      "user_likes": false,
      "id": "859811910782549_859815934115480"
    },
    {
      "created_time": "2015-09-09T02:55:37+0000",
      "from": {
        "name": "林財生",
        "id": "100000219547671"
      },
      "message": "重點在。。。何時槍決",
      "can_remove": false,
      "like_count": 2,
      "user_likes": false,
      "id": "859811910782549_859812690782471"
    }
  ]
}