{
  "title": "【更新】王力宏揪嬌妻當粉絲　讚二姊表現「完美」",
  "id": "20150823/675873",
  "link": "http://www.appledaily.com.tw/realtimenews/article/new/20150823/675873/",
  "comments": [
    {
      "created_time": "2015-08-23T07:35:24+0000",
      "from": {
        "name": "Sa Vivi",
        "id": "100002473081026"
      },
      "message": "以前窮到啃紅蘿蔔 如今香奈兒包不算啥囉\n真的嫁對人了 ))看康熙的",
      "can_remove": false,
      "like_count": 0,
      "user_likes": false,
      "id": "1006757676030920_1007061586000529"
    },
    {
      "created_time": "2015-08-23T07:30:35+0000",
      "from": {
        "name": "Colivaro Bruce",
        "id": "100009770564530"
      },
      "message": "眉毛畫成蠟筆小新有夠醜",
      "can_remove": false,
      "like_count": 0,
      "user_likes": false,
      "id": "1006757676030920_1007060442667310"
    }
  ]
}