{
  "title": "央視盜用影片　還嗆「央視用你素材又怎麼了」",
  "id": "20150912/690104",
  "link": "http://www.appledaily.com.tw/realtimenews/article/new/20150912/690104/",
  "comments": [
    {
      "created_time": "2015-09-11T20:59:06+0000",
      "from": {
        "name": "劉鼻水",
        "id": "100002638045761"
      },
      "message": "強國電視台你敢跟他玩",
      "can_remove": false,
      "like_count": 1,
      "user_likes": false,
      "id": "848073235313378_848079538646081"
    },
    {
      "created_time": "2015-09-11T20:44:49+0000",
      "from": {
        "name": "Shouyu Chen",
        "id": "100000428576475"
      },
      "message": "止元在FB上轉貼圖不附來源，還嗆劇照所有的製作人收版面廣告費",
      "can_remove": false,
      "like_count": 3,
      "user_likes": false,
      "id": "848073235313378_848076191979749"
    },
    {
      "created_time": "2015-09-11T20:41:05+0000",
      "from": {
        "name": "王元萬",
        "id": "100006112638576"
      },
      "message": "弄的過才奇怪",
      "can_remove": false,
      "like_count": 1,
      "user_likes": false,
      "id": "848073235313378_848075298646505"
    }
  ]
}