{
  "title": "美研究：女人較容易發展雙性戀",
  "id": "20150825/677422",
  "link": "http://www.appledaily.com.tw/realtimenews/article/new/20150825/677422/",
  "comments": [
    {
      "created_time": "2015-08-25T12:51:16+0000",
      "from": {
        "name": "吳旼諼",
        "id": "100004083287751"
      },
      "message": "還以為又是英國的研究",
      "can_remove": false,
      "like_count": 0,
      "user_likes": false,
      "id": "738701652908675_738775076234666"
    },
    {
      "created_time": "2015-08-25T12:32:31+0000",
      "from": {
        "name": "黃雅苓",
        "id": "100007270933907"
      },
      "message": "重點有很多......",
      "can_remove": false,
      "like_count": 0,
      "user_likes": false,
      "id": "738701652908675_738769616235212"
    },
    {
      "created_time": "2015-08-25T12:13:53+0000",
      "from": {
        "name": "Marbee Huang",
        "id": "1825174972"
      },
      "message": "「而對於異性選擇較少的女性來說，有較大可能與同性相戀。」\n沒看過拉子是大正妹還拒絕一堆異性追求者的嗎？哈哈哈…\n「研究認為，女性越早成功與男性交往，越不可能與同性發展關係。」\n因果關係顛倒囉～拉子是因為異性對自己較無吸引力,所以不會很早就與異性交往吧。",
      "can_remove": false,
      "like_count": 1,
      "user_likes": false,
      "id": "738701652908675_738763706235803"
    },
    {
      "created_time": "2015-08-25T11:59:33+0000",
      "from": {
        "name": "鍾佳璇",
        "id": "100004808955297"
      },
      "message": "胡說八道！",
      "can_remove": false,
      "like_count": 0,
      "user_likes": false,
      "id": "738701652908675_738760456236128"
    },
    {
      "created_time": "2015-08-25T11:22:35+0000",
      "from": {
        "name": "黃虎斑",
        "id": "1512060682"
      },
      "message": "重點是小舔舔沒男人愛, 就會變成愛女人嗎...",
      "can_remove": false,
      "like_count": 0,
      "user_likes": false,
      "id": "738701652908675_738749829570524"
    },
    {
      "created_time": "2015-08-25T11:08:08+0000",
      "from": {
        "name": "Tz Han Chen",
        "id": "100000173242807"
      },
      "message": "重點是根本不準",
      "can_remove": false,
      "like_count": 2,
      "user_likes": false,
      "id": "738701652908675_738746376237536"
    },
    {
      "created_time": "2015-08-25T10:55:47+0000",
      "from": {
        "name": "柯秀瑜",
        "id": "100001418337438"
      },
      "message": "重點是因有愛………",
      "can_remove": false,
      "like_count": 3,
      "user_likes": false,
      "id": "738701652908675_738743446237829"
    },
    {
      "created_time": "2015-08-25T10:52:10+0000",
      "from": {
        "name": "方玄輝",
        "id": "100000511186901"
      },
      "message": "重點要有男人來喜歡^_^",
      "can_remove": false,
      "like_count": 0,
      "user_likes": false,
      "id": "738701652908675_738742686237905"
    },
    {
      "created_time": "2015-08-25T10:37:52+0000",
      "from": {
        "name": "吳慰親",
        "id": "100004305095589"
      },
      "message": "重點也要有對象…",
      "can_remove": false,
      "like_count": 0,
      "user_likes": false,
      "id": "738701652908675_738739892904851"
    },
    {
      "created_time": "2015-08-25T09:43:20+0000",
      "from": {
        "name": "林奎伯",
        "id": "100000237751282"
      },
      "message": "重點要有錢....",
      "can_remove": false,
      "like_count": 1,
      "user_likes": false,
      "id": "738701652908675_738725992906241"
    }
  ]
}