{
  "title": "帶學生媽開房被抓姦　男師稱只是開解",
  "id": "20150911/689372",
  "link": "http://www.appledaily.com.tw/realtimenews/article/new/20150911/689372/",
  "comments": [
    {
      "created_time": "2015-09-11T01:44:37+0000",
      "from": {
        "name": "政璜 蔡",
        "id": "100002658491920"
      },
      "message": "官檢警忙著(抓猴)(捉鸡)(仙人跳)？\n死台胞，死老百姓，死不完？\n一一一\n中共刑法唯一死刑！\n高雄小林村三多路分社(雄檢博哥！炒天价卖不起訴書)(白巾验屍版)再流銷四百本？。台北巨蛋若有罪？ 高雄小村村三多路坑必死罪？",
      "can_remove": false,
      "like_count": 1,
      "user_likes": false,
      "id": "1008878185809173_1009001612463497"
    },
    {
      "created_time": "2015-09-11T01:17:15+0000",
      "from": {
        "name": "成奎安",
        "id": "100008830353213"
      },
      "message": "跟自己學生的媽媽上賓館，這個厲害！",
      "can_remove": false,
      "like_count": 0,
      "user_likes": false,
      "id": "1008878185809173_1008995685797423"
    },
    {
      "created_time": "2015-09-11T00:17:01+0000",
      "from": {
        "name": "張漢翔",
        "id": "100010311156952"
      },
      "message": "潑x酸。支持你",
      "can_remove": false,
      "like_count": 0,
      "user_likes": false,
      "id": "1008878185809173_1008964425800549"
    },
    {
      "created_time": "2015-09-11T00:08:01+0000",
      "from": {
        "name": "Misty Mimi",
        "id": "100004391956744"
      },
      "message": "開房間是為人師表大愛的行為...學生家庭觸礁感情不順更要深入關愛詳實瞭解....你們懂什麼！",
      "can_remove": false,
      "like_count": 0,
      "user_likes": false,
      "id": "1008878185809173_1008961855800806"
    },
    {
      "created_time": "2015-09-10T22:37:31+0000",
      "from": {
        "name": "王義雄",
        "id": "100003938865142"
      },
      "message": "我也是想要   深入  了解以前教的學生結婚後過的好不好，怕別人誤會就帶她去隱密處  開解  一下，幹嘛誤會我的為人，啊，抱歉，我的拉鍊沒拉好  解開 了，先拉一下",
      "can_remove": false,
      "like_count": 5,
      "user_likes": false,
      "id": "1008878185809173_1008922072471451"
    },
    {
      "created_time": "2015-09-10T22:12:01+0000",
      "from": {
        "name": "Jun Wei Chung",
        "category": "Blogger",
        "id": "729320167158203"
      },
      "message": "強國版阿基師！\n覺得學生生活有困難，想關心她，\n關心著關心著就「滑」進摩鐵了.......",
      "can_remove": false,
      "like_count": 9,
      "user_likes": false,
      "id": "1008878185809173_1008911769139148"
    }
  ]
}