{
  "title": "圖書館夢周公　小姐屁屁好吸睛",
  "id": "20150822/675787",
  "link": "http://www.appledaily.com.tw/realtimenews/article/new/20150822/675787/",
  "comments": [
    {
      "created_time": "2015-08-22T15:40:43+0000",
      "from": {
        "name": "陳怡欣",
        "id": "100010249595542"
      },
      "message": "【香蕉妹外送俱樂部】LINE：sexy986 想喝好茶找香蕉妹更多好茶還請線上咨詢哦~\n【裝笑 未成年 不在台灣的 看照不約的 請不要加 謝謝】\n香蕉妹打炮急救站+LINE：sexy986 愛愛口交洗澡（特殊服務看互動）\n饑渴的午夜.老二硬邦邦.精蟲上腦.無處釋放.打手槍不滿足\n就加入香蕉妹正妹急救站【賴：sexy986 】用心.貼心.誠心為您挑選\n讓你玩得開心.舒心.放心.(讓您爽爆回去）",
      "can_remove": false,
      "like_count": 0,
      "user_likes": false,
      "id": "953120848083544_953249091404053"
    },
    {
      "created_time": "2015-08-22T14:10:20+0000",
      "from": {
        "name": "黃啟斌",
        "id": "100000187194922"
      },
      "message": "一定是陸客",
      "can_remove": false,
      "like_count": 0,
      "user_likes": false,
      "id": "953120848083544_953203881408574"
    },
    {
      "created_time": "2015-08-22T14:05:27+0000",
      "from": {
        "name": "周琳琳",
        "id": "100009024874410"
      },
      "message": "他穿的那個超貼身內搭褲   本來就很容易跑出內褲痕跡來了 \n但好像很多人愛穿",
      "can_remove": false,
      "like_count": 0,
      "user_likes": false,
      "id": "953120848083544_953202584742037"
    },
    {
      "created_time": "2015-08-22T13:43:27+0000",
      "from": {
        "name": "Lie-Juian Lin",
        "id": "100001984320291"
      },
      "message": "第3世界化了\n\n外勞之子,\n\n中勞之子....????",
      "can_remove": false,
      "like_count": 0,
      "user_likes": false,
      "id": "953120848083544_953194818076147"
    },
    {
      "created_time": "2015-08-22T13:41:38+0000",
      "from": {
        "name": "朱建華",
        "id": "100003062526458"
      },
      "message": "這～也可以當新聞！！太混了吧",
      "can_remove": false,
      "like_count": 0,
      "user_likes": false,
      "id": "953120848083544_953194451409517"
    },
    {
      "created_time": "2015-08-22T13:03:06+0000",
      "from": {
        "name": "Fu Yuan Kuo",
        "id": "100000261616935"
      },
      "message": "[[[[《蘋果》看到網路文章後，前往圖書館尋找]]]]\n是吃飽沒事幹嗎？\n你領薪水領得安心嗎？",
      "can_remove": false,
      "like_count": 2,
      "user_likes": false,
      "id": "953120848083544_953168294745466"
    },
    {
      "created_time": "2015-08-22T13:00:42+0000",
      "from": {
        "name": "南天",
        "id": "100002644876774"
      },
      "message": "為了獎金甘為平果狗",
      "can_remove": false,
      "like_count": 0,
      "user_likes": false,
      "id": "953120848083544_953157761413186"
    },
    {
      "created_time": "2015-08-22T12:51:34+0000",
      "from": {
        "name": "牛美十",
        "id": "100009939432841"
      },
      "message": "這樣也發一則新聞？還真的跑到現場去看？",
      "can_remove": false,
      "like_count": 5,
      "user_likes": false,
      "id": "953120848083544_953122004750095"
    }
  ]
}